lm_cli/__init__.py
lm_cli/__main__.py
lm_cli/bootstrap.py
lm_cli/cli.py
lm_cli/constants.py
lm_cli/utils.py
lm_term-0.1.0.dist-info/entry_points.txt
lm_term-0.1.0.dist-info/LICENSE
lm_term-0.1.0.dist-info/METADATA
lm_term-0.1.0.dist-info/WHEEL
lm_term-0.1.0.dist-info/RECORD
