Metadata-Version: 2.3
Name: lm-term
Version: 0.1.0
Summary: Command-line interface for LLMs with advanced features like tool calling, file handling, and more.
License: MIT License
Keywords: llm,large language models,ai,cli,ai search,gpt,openai
Author: Vitalii Stepanenko
Author-email: mail@vitalii.in
Maintainer: Vitalii Stepanenko
Maintainer-email: mail@vitalii.in
Requires-Python: >=3.10
Classifier: Environment :: Console
Classifier: Intended Audience :: Developers
Classifier: Operating System :: OS Independent
Classifier: Programming Language :: Python :: 3
Classifier: Programming Language :: Python :: 3.10
Classifier: Programming Language :: Python :: 3.11
Classifier: Programming Language :: Python :: 3.12
Classifier: Programming Language :: Python :: 3.13
Classifier: License :: OSI Approved :: MIT License
Requires-Dist: ai-microcore (>=4.0.0.dev14,<4.1.0)
Requires-Dist: anthropic (>=0.52.0,<0.53.0)
Requires-Dist: google-generativeai (>=0.8.5,<0.9.0)
Requires-Dist: rich (>=13.6.0,<13.7.0)
Project-URL: Source Code, https://github.com/Nayjest/LLM-Console
